acsefunctions/__init__.py
acsefunctions/modules.py
acsefunctions-0.5.dist-info/LICENSE
acsefunctions-0.5.dist-info/METADATA
acsefunctions-0.5.dist-info/WHEEL
acsefunctions-0.5.dist-info/top_level.txt
acsefunctions-0.5.dist-info/RECORD
